odoo/addons/ssi_hr_dicipline/README.rst
odoo/addons/ssi_hr_dicipline/__init__.py
odoo/addons/ssi_hr_dicipline/__manifest__.py
odoo/addons/ssi_hr_dicipline/data/approval_template_data.xml
odoo/addons/ssi_hr_dicipline/data/ir_sequence_data.xml
odoo/addons/ssi_hr_dicipline/data/policy_template_data.xml
odoo/addons/ssi_hr_dicipline/data/sequence_template_data.xml
odoo/addons/ssi_hr_dicipline/i18n/ssi_hr_dicipline.pot
odoo/addons/ssi_hr_dicipline/models/__init__.py
odoo/addons/ssi_hr_dicipline/models/hr_dicipline.py
odoo/addons/ssi_hr_dicipline/models/hr_dicipline_reason.py
odoo/addons/ssi_hr_dicipline/models/hr_dicipline_type.py
odoo/addons/ssi_hr_dicipline/security/ir.model.access.csv
odoo/addons/ssi_hr_dicipline/security/ir_module_category_data.xml
odoo/addons/ssi_hr_dicipline/security/ir_rule_data.xml
odoo/addons/ssi_hr_dicipline/security/res_group_data.xml
odoo/addons/ssi_hr_dicipline/static/description/icon.png
odoo/addons/ssi_hr_dicipline/views/hr_dicipline_reason_views.xml
odoo/addons/ssi_hr_dicipline/views/hr_dicipline_type_views.xml
odoo/addons/ssi_hr_dicipline/views/hr_dicipline_views.xml
odoo14_addon_ssi_hr_dicipline-14.0.1.2.0.dist-info/METADATA
odoo14_addon_ssi_hr_dicipline-14.0.1.2.0.dist-info/WHEEL
odoo14_addon_ssi_hr_dicipline-14.0.1.2.0.dist-info/top_level.txt
odoo14_addon_ssi_hr_dicipline-14.0.1.2.0.dist-info/RECORD
